topsis_python/topsis.py
topsis_kjindal_101703299-1.0.1.dist-info/LICENSE.txt
topsis_kjindal_101703299-1.0.1.dist-info/METADATA
topsis_kjindal_101703299-1.0.1.dist-info/WHEEL
topsis_kjindal_101703299-1.0.1.dist-info/entry_points.txt
topsis_kjindal_101703299-1.0.1.dist-info/top_level.txt
topsis_kjindal_101703299-1.0.1.dist-info/RECORD
